README.md
pyproject.toml
setup.py
src/mathprocore/__init__.py
src/mathprocore.egg-info/PKG-INFO
src/mathprocore.egg-info/SOURCES.txt
src/mathprocore.egg-info/dependency_links.txt
src/mathprocore.egg-info/requires.txt
src/mathprocore.egg-info/top_level.txt
src/mathprocore/Question/__init__.py
src/mathprocore/Question/auto_fitter.py
src/mathprocore/Question/image.py
src/mathprocore/Question/matrix.py
src/mathprocore/Question/nums.py
src/mathprocore/Question/question.py
src/mathprocore/Question/helpers/__init__.py
src/mathprocore/Question/helpers/exprh.py
src/mathprocore/Question/helpers/imgh.py
src/mathprocore/Question/helpers/csympy/__init__.py
src/mathprocore/Question/helpers/csympy/parsing/__init__.py
src/mathprocore/Question/helpers/csympy/parsing/ast_parser.py
src/mathprocore/Question/helpers/csympy/parsing/mathematica.py
src/mathprocore/Question/helpers/csympy/parsing/maxima.py
src/mathprocore/Question/helpers/csympy/parsing/sym_expr.py
src/mathprocore/Question/helpers/csympy/parsing/sympy_parser.py
src/mathprocore/Question/helpers/csympy/parsing/autolev/__init__.py
src/mathprocore/Question/helpers/csympy/parsing/autolev/_listener_autolev_antlr.py
src/mathprocore/Question/helpers/csympy/parsing/autolev/_parse_autolev_antlr.py
src/mathprocore/Question/helpers/csympy/parsing/autolev/_antlr/__init__.py
src/mathprocore/Question/helpers/csympy/parsing/autolev/_antlr/autolevlexer.py
src/mathprocore/Question/helpers/csympy/parsing/autolev/_antlr/autolevlistener.py
src/mathprocore/Question/helpers/csympy/parsing/autolev/_antlr/autolevparser.py
src/mathprocore/Question/helpers/csympy/parsing/c/__init__.py
src/mathprocore/Question/helpers/csympy/parsing/c/c_parser.py
src/mathprocore/Question/helpers/csympy/parsing/fortran/__init__.py
src/mathprocore/Question/helpers/csympy/parsing/fortran/fortran_parser.py
src/mathprocore/Question/helpers/csympy/parsing/latex/__init__.py
src/mathprocore/Question/helpers/csympy/parsing/latex/_build_latex_antlr.py
src/mathprocore/Question/helpers/csympy/parsing/latex/_parse_latex_antlr.py
src/mathprocore/Question/helpers/csympy/parsing/latex/errors.py
src/mathprocore/Question/helpers/csympy/parsing/latex/_antlr/__init__.py
