Metadata-Version: 2.1
Name: mathprocore
Version: 0.0.2
Summary: Use MathPro to generate unlimited math practice problems from question templates!
Home-page: https://github.com/Nimsi123/MathProgram
Author: Nima Rahmanian
Author-email: nimarahmanian8@gmail.com
License: UNKNOWN
Platform: UNKNOWN
Classifier: Programming Language :: Python :: 3
Classifier: License :: OSI Approved :: MIT License
Classifier: Operating System :: OS Independent
Requires-Python: >=3.6
